ftrace/__init__.py
ftrace/exceptions.py
ftrace/filehelper.py
ftrace/ftrace.py
ftrace/parsers.py
ftrace/sockaddr.py
ftrace/syscallparam.py
ftrace/syscalls.py
ftrace/tracers.py
ftrace-0.0.1.dist-info/LICENSE
ftrace-0.0.1.dist-info/METADATA
ftrace-0.0.1.dist-info/WHEEL
ftrace-0.0.1.dist-info/top_level.txt
ftrace-0.0.1.dist-info/RECORD
