Metadata-Version: 2.1
Name: ftrace
Version: 0.0.1
Summary: library for reading ftrace data
Home-page: https://github.com/manfred-kaiser/python-ftrace
Author: Manfred Kaiser
Author-email: manfred.kaiser@logfile.at
License: UNKNOWN
Platform: UNKNOWN
Classifier: Programming Language :: Python :: 3
Classifier: License :: OSI Approved :: GNU Lesser General Public License v3 (LGPLv3)
Classifier: Operating System :: POSIX :: Linux
Classifier: Topic :: System :: Operating System Kernels :: Linux
Requires-Python: >= 3.5
